blinker/__init__.py
blinker/_saferef.py
blinker/_utilities.py
blinker/base.py
blinker/py.typed
blinker-1.6.1.dist-info/LICENSE.rst
blinker-1.6.1.dist-info/METADATA
blinker-1.6.1.dist-info/WHEEL
blinker-1.6.1.dist-info/top_level.txt
blinker-1.6.1.dist-info/RECORD
