Metadata-Version: 2.1
Name: blinker
Version: 1.6.1
Summary: Fast, simple object-to-object and broadcast signaling
Author-email: Jason Kirtland <jek@discorporate.us>
Maintainer-email: Pallets Ecosystem <contact@palletsprojects.com>
License: MIT License
Project-URL: Homepage, https://blinker.readthedocs.io
Project-URL: Documentation, https://blinker.readthedocs.io
Project-URL: Source Code, https://github.com/pallets-eco/blinker/
Project-URL: Issue Tracker, https://github.com/pallets-eco/blinker/issues/
Project-URL: Chat, https://discord.gg/pallets
Keywords: signal,emit,events,broadcast
Classifier: Development Status :: 5 - Production/Stable
Classifier: Intended Audience :: Developers
Classifier: License :: OSI Approved :: MIT License
Classifier: Operating System :: OS Independent
Classifier: Programming Language :: Python
Classifier: Topic :: Software Development :: Libraries
Requires-Python: >=3.7
License-File: LICENSE.rst
